django_view_decorator/__about__.py
django_view_decorator/__init__.py
django_view_decorator/app_config.py
django_view_decorator/apps.py
django_view_decorator/conf.py
django_view_decorator/decorators.py
django_view_decorator/urls.py
django_view_decorator/urls_utils.py
django_view_decorator/management/commands/list_views.py
django_view_decorator-0.0.4.dist-info/METADATA
django_view_decorator-0.0.4.dist-info/WHEEL
django_view_decorator-0.0.4.dist-info/licenses/LICENSE.txt
django_view_decorator-0.0.4.dist-info/RECORD
