Metadata-Version: 2.1
Name: django-view-decorator
Version: 0.0.4
Summary: django-view-decorator is decorator aimed at bringing locality of behaviour to the connection between a URL and a view in Django.
Project-URL: Documentation, https://django-view-decorator.readthedocs.io/
Project-URL: Issues, https://github.com/valberg/django-view-decorator/issues
Project-URL: Source, https://github.com/valberg/django-view-decorator
Author-email: Víðir Valberg Guðmundsson <valberg@orn.li>
License-Expression: MIT
License-File: LICENSE.txt
Classifier: Development Status :: 3 - Alpha
Classifier: Programming Language :: Python
Classifier: Programming Language :: Python :: 3.10
Classifier: Programming Language :: Python :: 3.11
Classifier: Programming Language :: Python :: Implementation :: CPython
Classifier: Programming Language :: Python :: Implementation :: PyPy
Requires-Python: >=3.10
Requires-Dist: django>=3.2
